uns_kit/__init__.py
uns_kit/cli.py
uns_kit/client.py
uns_kit/config.py
uns_kit/packet.py
uns_kit/templates/default/README.md
uns_kit/templates/default/pyproject.toml
uns_kit/templates/default/src/main.py
uns_kit/topic_builder.py
uns_kit-0.0.4.dist-info/METADATA
uns_kit-0.0.4.dist-info/WHEEL
uns_kit-0.0.4.dist-info/entry_points.txt
uns_kit-0.0.4.dist-info/RECORD
