Metadata-Version: 2.4
Name: uns-kit
Version: 0.0.4
Summary: Lightweight Python UNS MQTT client (pub/sub + infra topics)
License: MIT
Author: Aljoša Vister
Author-email: aljosa.vister@gmail.com
Requires-Python: >=3.10,<4.0
Classifier: License :: OSI Approved :: MIT License
Classifier: Programming Language :: Python :: 3
Classifier: Programming Language :: Python :: 3.10
Classifier: Programming Language :: Python :: 3.11
Classifier: Programming Language :: Python :: 3.12
Classifier: Programming Language :: Python :: 3.13
Classifier: Programming Language :: Python :: 3.14
Requires-Dist: asyncio-mqtt (>=0.16.1,<0.17.0)
Requires-Dist: click (>=8.1.7,<9.0.0)
